maylng/__init__.py
maylng/client.py
maylng/email_address_service.py
maylng/email_service.py
maylng/errors.py
maylng/http_client.py
maylng/types.py
maylng-0.3.1b2.dist-info/METADATA
maylng-0.3.1b2.dist-info/WHEEL
maylng-0.3.1b2.dist-info/licenses/LICENSE
maylng-0.3.1b2.dist-info/RECORD
