Metadata-Version: 2.4
Name: maylng
Version: 0.3.1b2
Summary: Maylng - Python SDK for agentic email management. Create email addresses and send emails programmatically for AI agents.
Project-URL: Homepage, https://github.com/maylng/mayl-sdk
Project-URL: Documentation, https://docs.maylng.com
Project-URL: Repository, https://github.com/maylng/mayl-sdk.git
Project-URL: Issues, https://github.com/maylng/mayl-sdk/issues
Author-email: KnextKoder <hello@knextkoder.com>
License-Expression: MIT
License-File: LICENSE
Keywords: agentic,agents,ai,automation,email,email-api,maylng,python,sdk,smtp,temporary-email
Classifier: Development Status :: 4 - Beta
Classifier: Intended Audience :: Developers
Classifier: License :: OSI Approved :: MIT License
Classifier: Programming Language :: Python :: 3
Classifier: Programming Language :: Python :: 3.8
Classifier: Programming Language :: Python :: 3.9
Classifier: Programming Language :: Python :: 3.10
Classifier: Programming Language :: Python :: 3.11
Classifier: Programming Language :: Python :: 3.12
Classifier: Topic :: Communications :: Email
Classifier: Topic :: Software Development :: Libraries :: Python Modules
Requires-Python: >=3.8
Requires-Dist: httpx>=0.25.0
Requires-Dist: pydantic[email]>=2.0.0
Requires-Dist: typing-extensions>=4.0.0; python_version < '3.10'
Provides-Extra: dev
Requires-Dist: black>=23.0.0; extra == 'dev'
Requires-Dist: flake8>=6.0.0; extra == 'dev'
Requires-Dist: isort>=5.12.0; extra == 'dev'
Requires-Dist: mypy>=1.0.0; extra == 'dev'
Requires-Dist: pytest-asyncio>=0.21.0; extra == 'dev'
Requires-Dist: pytest>=7.0.0; extra == 'dev'
